minipyg/__init__.py
minipyg/minipyg.py
minipyg-0.0.1.dist-info/LICENCE
minipyg-0.0.1.dist-info/METADATA
minipyg-0.0.1.dist-info/WHEEL
minipyg-0.0.1.dist-info/entry_points.txt
minipyg-0.0.1.dist-info/top_level.txt
minipyg-0.0.1.dist-info/RECORD
