Metadata-Version: 2.1
Name: minipyg
Version: 0.0.1
Summary: A simple(st) python dependency manager
Classifier: Programming Language :: Python :: 3
Classifier: License :: OSI Approved :: MIT License
Classifier: Operating System :: OS Independent
Requires-Python: >=3.6
License-File: LICENCE
